kitgenerator/__init__.py
kitgenerator/__main__.py
kitgenerator/app.py
kitgenerator/cli.py
kitgenerator/extract.py
kit_generator-1.0.0.dist-info/METADATA
kit_generator-1.0.0.dist-info/WHEEL
kit_generator-1.0.0.dist-info/entry_points.txt
kit_generator-1.0.0.dist-info/top_level.txt
kit_generator-1.0.0.dist-info/RECORD
